colabutils/__init__.py
colabutils/audio.py
colabutils/gcp.py
colabutils/gdrive.py
colabutils/vision.py
colabutils/vision_utils.py
colabutils/webcam.py
colabutils-0.1.3.dist-info/LICENSE
colabutils-0.1.3.dist-info/METADATA
colabutils-0.1.3.dist-info/WHEEL
colabutils-0.1.3.dist-info/top_level.txt
colabutils-0.1.3.dist-info/RECORD
