Metadata-Version: 2.1
Name: colabutils
Version: 0.1.3
Summary: Utilities to use with Google Colaboratory
Home-page: https://github.com/arki1/colabutils
Author: ARKi1
Author-email: fabricio@arki1.com
License: GNU GENERAL PUBLIC LICENSE
Requires-Dist: google-api-python-client (>=1.6.7)
Requires-Dist: ipython (>=5.5.0)
